{
  "date": "2025-12-15",
  "market": {
    "risk_on": false,
    "broad_strength": 0.18000000000000005,
    "advice": "DEFENSE"
  },
  "industry_boards": [
    {
      "code": "BK0474",
      "name": "保险",
      "type": "industry",
      "ret": 0.031,
      "pop": -0.462092,
      "persistence": 3,
      "dispersion": 0.011325,
      "breadth": 1.0,
      "score": 1.813363,
      "stance": "STRONG_BUY",
      "is_new": false,
      "core_stocks": [
        {
          "code": "601318",
          "name": "中国平安",
          "ret": 0.0494,
          "core": -0.375566
        },
        {
          "code": "601601",
          "name": "中国太保",
          "ret": 0.0361,
          "core": -0.558492
        },
        {
          "code": "601336",
          "name": "新华保险",
          "ret": 0.0257,
          "core": -0.73246
        }
      ]
    },
    {
      "code": "BK0482",
      "name": "商业百货",
      "type": "industry",
      "ret": 0.0267,
      "pop": 0.543822,
      "persistence": 3,
      "dispersion": 0.021245,
      "breadth": 1.0,
      "score": 2.632764,
      "stance": "STRONG_BUY",
      "is_new": false,
      "core_stocks": [
        {
          "code": "600693",
          "name": "东百集团",
          "ret": 0.1,
          "core": 2.350112
        },
        {
          "code": "600865",
          "name": "百大集团",
          "ret": 0.1002,
          "core": 1.924086
        },
        {
          "code": "002697",
          "name": "红旗连锁",
          "ret": 0.1007,
          "core": 1.70126
        }
      ]
    },
    {
      "code": "BK0438",
      "name": "食品饮料",
      "type": "industry",
      "ret": 0.0204,
      "pop": 1.549736,
      "persistence": 3,
      "dispersion": 0.03796,
      "breadth": 1.0,
      "score": 3.475934,
      "stance": "STRONG_BUY",
      "is_new": false,
      "core_stocks": [
        {
          "code": "300997",
          "name": "欢乐家",
          "ret": 0.1998,
          "core": 2.087471
        },
        {
          "code": "920786",
          "name": "骑士乳业",
          "ret": 0.0897,
          "core": 1.990224
        },
        {
          "code": "002702",
          "name": "海欣食品",
          "ret": 0.0532,
          "core": 1.622405
        }
      ]
    },
    {
      "code": "BK0471",
      "name": "化纤行业",
      "type": "industry",
      "ret": 0.0196,
      "pop": -0.022004,
      "persistence": 3,
      "dispersion": 0.016134,
      "breadth": 1.0,
      "score": 0.741885,
      "stance": "BUY",
      "is_new": true,
      "core_stocks": [
        {
          "code": "300876",
          "name": "蒙泰高新",
          "ret": 0.0558,
          "core": 0.778839
        },
        {
          "code": "000949",
          "name": "新乡化纤",
          "ret": 0.0764,
          "core": 0.552912
        },
        {
          "code": "002064",
          "name": "华峰化学",
          "ret": 0.0691,
          "core": 0.012835
        }
      ]
    },
    {
      "code": "BK0732",
      "name": "贵金属",
      "type": "industry",
      "ret": 0.0172,
      "pop": -0.378265,
      "persistence": 3,
      "dispersion": 0.015967,
      "breadth": 0.9,
      "score": -0.291274,
      "stance": "WATCH",
      "is_new": false,
      "core_stocks": [
        {
          "code": "300139",
          "name": "晓程科技",
          "ret": -0.0122,
          "core": 0.117109
        },
        {
          "code": "001337",
          "name": "四川黄金",
          "ret": 0.0373,
          "core": -0.163558
        },
        {
          "code": "000506",
          "name": "招金黄金",
          "ret": 0.0317,
          "core": -0.200962
        }
      ]
    },
    {
      "code": "BK0479",
      "name": "钢铁行业",
      "type": "industry",
      "ret": 0.0144,
      "pop": 0.208518,
      "persistence": 3,
      "dispersion": 0.026515,
      "breadth": 1.0,
      "score": 0.133977,
      "stance": "WATCH",
      "is_new": true,
      "core_stocks": [
        {
          "code": "002478",
          "name": "常宝股份",
          "ret": 0.0348,
          "core": 0.926916
        },
        {
          "code": "600399",
          "name": "抚顺特钢",
          "ret": 0.1,
          "core": 0.876639
        },
        {
          "code": "000825",
          "name": "太钢不锈",
          "ret": 0.0995,
          "core": 0.485068
        }
      ]
    },
    {
      "code": "BK0539",
      "name": "综合行业",
      "type": "industry",
      "ret": 0.0128,
      "pop": -0.336352,
      "persistence": 3,
      "dispersion": 0.038203,
      "breadth": 1.0,
      "score": -1.344037,
      "stance": "AVOID",
      "is_new": false,
      "core_stocks": [
        {
          "code": "000632",
          "name": "三木集团",
          "ret": 0.0655,
          "core": 1.300635
        },
        {
          "code": "002053",
          "name": "云南能投",
          "ret": 0.1,
          "core": 0.502891
        },
        {
          "code": "600113",
          "name": "浙江东日",
          "ret": 0.1001,
          "core": 0.500975
        }
      ]
    },
    {
      "code": "BK1018",
      "name": "橡胶制品",
      "type": "industry",
      "ret": 0.0124,
      "pop": -0.147744,
      "persistence": 3,
      "dispersion": 0.082329,
      "breadth": 1.0,
      "score": -1.226345,
      "stance": "AVOID",
      "is_new": false,
      "core_stocks": [
        {
          "code": "920665",
          "name": "科强股份",
          "ret": 0.2997,
          "core": 6.706639
        },
        {
          "code": "920098",
          "name": "科隆新材",
          "ret": 0.09,
          "core": 1.355685
        },
        {
          "code": "603650",
          "name": "彤程新材",
          "ret": 0.0568,
          "core": 0.488244
        }
      ]
    },
    {
      "code": "BK1042",
      "name": "医药商业",
      "type": "industry",
      "ret": 0.0107,
      "pop": -0.126787,
      "persistence": 3,
      "dispersion": 0.025174,
      "breadth": 1.0,
      "score": -1.016276,
      "stance": "AVOID",
      "is_new": false,
      "core_stocks": [
        {
          "code": "000950",
          "name": "重药控股",
          "ret": 0.1005,
          "core": 1.687387
        },
        {
          "code": "603122",
          "name": "合富中国",
          "ret": 0.0606,
          "core": 1.179257
        },
        {
          "code": "301126",
          "name": "达嘉维康",
          "ret": 0.0672,
          "core": 0.826644
        }
      ]
    },
    {
      "code": "BK0477",
      "name": "酿酒行业",
      "type": "industry",
      "ret": 0.0086,
      "pop": 0.082778,
      "persistence": 3,
      "dispersion": 0.023951,
      "breadth": 1.0,
      "score": -0.856424,
      "stance": "AVOID",
      "is_new": true,
      "core_stocks": [
        {
          "code": "000995",
          "name": "皇台酒业",
          "ret": 0.1002,
          "core": 0.878304
        },
        {
          "code": "600573",
          "name": "惠泉啤酒",
          "ret": 0.0203,
          "core": -0.253555
        },
        {
          "code": "600199",
          "name": "金种子酒",
          "ret": 0.0411,
          "core": -0.496241
        }
      ]
    }
  ],
  "concept_boards": [
    {
      "code": "BK0892",
      "name": "乳业",
      "type": "concept",
      "ret": 0.0374,
      "pop": 0.040865,
      "persistence": 3,
      "dispersion": 0.024092,
      "breadth": 1.0,
      "score": 3.017521,
      "stance": "STRONG_BUY",
      "is_new": false,
      "core_stocks": [
        {
          "code": "920786",
          "name": "骑士乳业",
          "ret": 0.0897,
          "core": 1.990224
        },
        {
          "code": "002329",
          "name": "皇氏集团",
          "ret": 0.1005,
          "core": 1.162908
        },
        {
          "code": "605339",
          "name": "南侨食品",
          "ret": 0.1002,
          "core": 0.65208
        }
      ]
    },
    {
      "code": "BK0933",
      "name": "退税商店",
      "type": "concept",
      "ret": 0.0305,
      "pop": -0.357309,
      "persistence": 3,
      "dispersion": 0.037217,
      "breadth": 1.0,
      "score": 1.058724,
      "stance": "BUY",
      "is_new": false,
      "core_stocks": [
        {
          "code": "600865",
          "name": "百大集团",
          "ret": 0.1002,
          "core": 1.924086
        },
        {
          "code": "002187",
          "name": "广百股份",
          "ret": 0.0996,
          "core": 0.858217
        },
        {
          "code": "600628",
          "name": "新世界",
          "ret": 0.0743,
          "core": 0.656495
        }
      ]
    },
    {
      "code": "BK1082",
      "name": "噪声防治",
      "type": "concept",
      "ret": 0.0277,
      "pop": -0.462092,
      "persistence": 3,
      "dispersion": 0.033852,
      "breadth": 0.625,
      "score": 0.502965,
      "stance": "BUY",
      "is_new": true,
      "core_stocks": [
        {
          "code": "300980",
          "name": "祥源新材",
          "ret": 0.0627,
          "core": 0.68155
        },
        {
          "code": "688485",
          "name": "九州一轨",
          "ret": 0.0906,
          "core": 0.639016
        },
        {
          "code": "300169",
          "name": "天晟新材",
          "ret": 0.0465,
          "core": 0.300303
        }
      ]
    },
    {
      "code": "BK1132",
      "name": "MLOps概念",
      "type": "concept",
      "ret": 0.022,
      "pop": -0.483048,
      "persistence": 3,
      "dispersion": 0.058992,
      "breadth": 0.4,
      "score": -0.506468,
      "stance": "AVOID",
      "is_new": true,
      "core_stocks": [
        {
          "code": "688031",
          "name": "星环科技-U",
          "ret": 0.1724,
          "core": 3.598414
        },
        {
          "code": "300520",
          "name": "科大国创",
          "ret": 0.0896,
          "core": 2.342427
        },
        {
          "code": "300365",
          "name": "恒华科技",
          "ret": 0.0258,
          "core": -0.410865
        }
      ]
    },
    {
      "code": "BK1026",
      "name": "调味品概念",
      "type": "concept",
      "ret": 0.021,
      "pop": 0.040865,
      "persistence": 3,
      "dispersion": 0.034554,
      "breadth": 1.0,
      "score": 0.578566,
      "stance": "BUY",
      "is_new": true,
      "core_stocks": [
        {
          "code": "920786",
          "name": "骑士乳业",
          "ret": 0.0897,
          "core": 1.990224
        },
        {
          "code": "600186",
          "name": "莲花控股",
          "ret": 0.1004,
          "core": 1.043596
        },
        {
          "code": "603696",
          "name": "安记食品",
          "ret": 0.0264,
          "core": 0.977727
        }
      ]
    },
    {
      "code": "BK0949",
      "name": "氦气概念",
      "type": "concept",
      "ret": 0.0206,
      "pop": -0.357309,
      "persistence": 3,
      "dispersion": 0.028122,
      "breadth": 1.0,
      "score": -0.176306,
      "stance": "WATCH",
      "is_new": false,
      "core_stocks": [
        {
          "code": "002639",
          "name": "雪人集团",
          "ret": 0.1002,
          "core": 1.379849
        },
        {
          "code": "301286",
          "name": "侨源股份",
          "ret": 0.0485,
          "core": 0.31289
        },
        {
          "code": "300435",
          "name": "中泰股份",
          "ret": 0.0482,
          "core": 0.095853
        }
      ]
    },
    {
      "code": "BK0994",
      "name": "空间站概念",
      "type": "concept",
      "ret": 0.0206,
      "pop": -0.315396,
      "persistence": 3,
      "dispersion": 0.036378,
      "breadth": 1.0,
      "score": -0.210126,
      "stance": "WATCH",
      "is_new": false,
      "core_stocks": [
        {
          "code": "002413",
          "name": "雷科防务",
          "ret": 0.1003,
          "core": 4.28403
        },
        {
          "code": "600879",
          "name": "航天电子",
          "ret": 0.1001,
          "core": 1.407278
        },
        {
          "code": "000901",
          "name": "航天科技",
          "ret": 0.0425,
          "core": 1.030395
        }
      ]
    },
    {
      "code": "BK1199",
      "name": "2025三季报预减",
      "type": "concept",
      "ret": 0.0169,
      "pop": -0.483048,
      "persistence": 3,
      "dispersion": 0.027102,
      "breadth": 0.5,
      "score": -0.917203,
      "stance": "AVOID",
      "is_new": true,
      "core_stocks": [
        {
          "code": "603992",
          "name": "松霖科技",
          "ret": 0.0695,
          "core": 0.053316
        },
        {
          "code": "688378",
          "name": "奥来德",
          "ret": 0.0475,
          "core": 0.002865
        },
        {
          "code": "300821",
          "name": "东岳硅材",
          "ret": 0.016,
          "core": -0.560666
        }
      ]
    },
    {
      "code": "BK1147",
      "name": "SPD概念",
      "type": "concept",
      "ret": 0.0153,
      "pop": -0.378265,
      "persistence": 3,
      "dispersion": 0.030563,
      "breadth": 0.9,
      "score": -0.988613,
      "stance": "AVOID",
      "is_new": false,
      "core_stocks": [
        {
          "code": "000950",
          "name": "重药控股",
          "ret": 0.1005,
          "core": 1.687387
        },
        {
          "code": "603122",
          "name": "合富中国",
          "ret": 0.0606,
          "core": 1.179257
        },
        {
          "code": "301584",
          "name": "建发致新",
          "ret": 0.0148,
          "core": -0.08307
        }
      ]
    },
    {
      "code": "BK0849",
      "name": "京东金融",
      "type": "concept",
      "ret": 0.0152,
      "pop": -0.399222,
      "persistence": 3,
      "dispersion": 0.035052,
      "breadth": 0.8,
      "score": -1.105368,
      "stance": "AVOID",
      "is_new": false,
      "core_stocks": [
        {
          "code": "600693",
          "name": "东百集团",
          "ret": 0.1,
          "core": 2.350112
        },
        {
          "code": "300300",
          "name": "海峡创新",
          "ret": 0.0615,
          "core": 2.211419
        },
        {
          "code": "000555",
          "name": "神州信息",
          "ret": 0.0129,
          "core": -0.675746
        }
      ]
    }
  ],
  "indices": {
    "CSI100": {
      "open": 443445.0,
      "high": 447000.0,
      "low": 442587.0,
      "close": 442666.0,
      "ret": -0.8,
      "volume": 73552141.0,
      "turnover": 235759903069.9
    },
    "HS300": {
      "open": 455000.0,
      "high": 459505.0,
      "low": 454844.0,
      "close": 455274.0,
      "ret": -0.62,
      "volume": 165927822.0,
      "turnover": 420708435861.7
    },
    "CSI500": {
      "open": 712138.0,
      "high": 717715.0,
      "low": 711068.0,
      "close": 711574.0,
      "ret": -0.75,
      "volume": 170418686.0,
      "turnover": 298280414449.5
    },
    "CSI1000": {
      "open": 732448.0,
      "high": 737561.0,
      "low": 730583.0,
      "close": 731232.0,
      "ret": -0.8,
      "volume": 218733412.0,
      "turnover": 368900627496.3
    },
    "CSI2000": {
      "open": 309012.0,
      "high": 312011.0,
      "low": 308045.0,
      "close": 309528.0,
      "ret": -0.21,
      "volume": 315465753.0,
      "turnover": 408589264312.0
    },
    "SHCOMP": {
      "open": 386540.0,
      "high": 389698.0,
      "low": 386363.0,
      "close": 386901.0,
      "ret": -0.52,
      "volume": 495514027.0,
      "turnover": 757236262209.2
    },
    "hs300": {
      "open": 455000.0,
      "high": 459505.0,
      "low": 454844.0,
      "close": 455274.0,
      "ret": -0.62,
      "volume": 165927822.0,
      "turnover": 420708435861.7
    },
    "csi1000": {
      "open": 732448.0,
      "high": 737561.0,
      "low": 730583.0,
      "close": 731232.0,
      "ret": -0.8,
      "volume": 218733412.0,
      "turnover": 368900627496.3
    },
    "shcomp": {
      "open": 386540.0,
      "high": 389698.0,
      "low": 386363.0,
      "close": 386901.0,
      "ret": -0.52,
      "volume": 495514027.0,
      "turnover": 757236262209.2
    }
  },
  "market_indices": {
    "SHCOMP": {
      "name": "上证指数",
      "open": 3865.4,
      "high": 3896.98,
      "low": 3863.63,
      "close": 3869.01,
      "ret": -0.0052,
      "volume": 495514027.0,
      "turnover": 757236262209.2
    },
    "SZCOMP": {
      "name": "深证成指",
      "open": 13150.43,
      "high": 13244.03,
      "low": 13111.38,
      "close": 13114.3,
      "ret": -0.0109,
      "volume": 619992053.0,
      "turnover": 997823554867.9944
    },
    "CYBZ": {
      "name": "创业板指",
      "open": 3157.32,
      "high": 3184.62,
      "low": 3135.66,
      "close": 3138.29,
      "ret": -0.0176,
      "volume": 185802105.0,
      "turnover": 466817429071.71
    },
    "KCB50": {
      "name": "科创50",
      "open": 1333.36,
      "high": 1343.78,
      "low": 1318.53,
      "close": 1319.38,
      "ret": -0.0219,
      "volume": 8403216.0,
      "turnover": 57913146063.0
    },
    "BJ50": {
      "name": "北证50",
      "open": 1443.07,
      "high": 1453.83,
      "low": 1430.17,
      "close": 1432.52,
      "ret": -0.0105,
      "volume": 8918586.0,
      "turnover": 20840887324.0
    }
  },
  "disclaimer": "本页面仅为个人研究与技术演示，不构成投资建议。"
}