{
  "date": "2026-03-31",
  "market": {
    "risk_on": false,
    "broad_strength": 0.8600000000000001,
    "advice": "DEFENSE"
  },
  "industry_boards": [
    {
      "code": "BK1564",
      "name": "体育Ⅲ",
      "type": "industry",
      "ret": 0.0604,
      "pop": -0.479943,
      "persistence": 3,
      "dispersion": 0.03925,
      "breadth": 1.0,
      "score": 0.90863,
      "stance": "BUY",
      "is_new": false,
      "core_stocks": [
        {
          "code": "600158",
          "name": "中体产业",
          "ret": 0.1,
          "core": 1.445678
        },
        {
          "code": "002858",
          "name": "力盛体育",
          "ret": 0.0215,
          "core": -0.012076
        }
      ]
    },
    {
      "code": "BK1273",
      "name": "体育Ⅱ",
      "type": "industry",
      "ret": 0.0604,
      "pop": -0.479943,
      "persistence": 3,
      "dispersion": 0.03895,
      "breadth": 1.0,
      "score": 0.914448,
      "stance": "BUY",
      "is_new": false,
      "core_stocks": [
        {
          "code": "600158",
          "name": "中体产业",
          "ret": 0.1,
          "core": 1.445678
        },
        {
          "code": "002858",
          "name": "力盛体育",
          "ret": 0.0221,
          "core": -0.007108
        }
      ]
    },
    {
      "code": "BK1378",
      "name": "其他能源发电",
      "type": "industry",
      "ret": 0.0573,
      "pop": -0.479943,
      "persistence": 3,
      "dispersion": 0.0432,
      "breadth": 1.0,
      "score": 0.659562,
      "stance": "BUY",
      "is_new": true,
      "core_stocks": [
        {
          "code": "002616",
          "name": "长青集团",
          "ret": 0.0141,
          "core": 0.195694
        },
        {
          "code": "000631",
          "name": "顺发恒能",
          "ret": 0.1005,
          "core": -0.164068
        }
      ]
    },
    {
      "code": "BK1521",
      "name": "摩托车",
      "type": "industry",
      "ret": 0.0562,
      "pop": -0.325123,
      "persistence": 3,
      "dispersion": 0.073185,
      "breadth": 0.888889,
      "score": 0.624179,
      "stance": "BUY",
      "is_new": true,
      "core_stocks": [
        {
          "code": "920058",
          "name": "华洋赛车",
          "ret": 0.2353,
          "core": 2.957979
        },
        {
          "code": "603787",
          "name": "新日股份",
          "ret": 0.0812,
          "core": 1.500983
        },
        {
          "code": "003033",
          "name": "征和工业",
          "ret": 0.1,
          "core": 0.865302
        }
      ]
    },
    {
      "code": "BK1531",
      "name": "商用载客车",
      "type": "industry",
      "ret": 0.0519,
      "pop": -0.387051,
      "persistence": 3,
      "dispersion": 0.028543,
      "breadth": 1.0,
      "score": 0.884151,
      "stance": "BUY",
      "is_new": true,
      "core_stocks": [
        {
          "code": "600303",
          "name": "曙光股份",
          "ret": 0.0469,
          "core": 0.703687
        },
        {
          "code": "000957",
          "name": "中通客车",
          "ret": 0.0469,
          "core": 0.265951
        },
        {
          "code": "600686",
          "name": "金龙汽车",
          "ret": 0.0565,
          "core": -0.098931
        }
      ]
    },
    {
      "code": "BK1394",
      "name": "轨交设备Ⅲ",
      "type": "industry",
      "ret": 0.0442,
      "pop": 0.325123,
      "persistence": 3,
      "dispersion": 0.045166,
      "breadth": 1.0,
      "score": 1.479133,
      "stance": "BUY",
      "is_new": true,
      "core_stocks": [
        {
          "code": "920027",
          "name": "交大铁发",
          "ret": 0.1704,
          "core": 3.758692
        },
        {
          "code": "301048",
          "name": "金鹰重工",
          "ret": 0.1998,
          "core": 2.481222
        },
        {
          "code": "300960",
          "name": "通业科技",
          "ret": 0.1267,
          "core": 1.335906
        }
      ]
    },
    {
      "code": "BK1236",
      "name": "轨交设备Ⅱ",
      "type": "industry",
      "ret": 0.0442,
      "pop": 0.325123,
      "persistence": 3,
      "dispersion": 0.045166,
      "breadth": 1.0,
      "score": 1.479133,
      "stance": "BUY",
      "is_new": true,
      "core_stocks": [
        {
          "code": "920027",
          "name": "交大铁发",
          "ret": 0.1704,
          "core": 3.758692
        },
        {
          "code": "301048",
          "name": "金鹰重工",
          "ret": 0.1998,
          "core": 2.481222
        },
        {
          "code": "300960",
          "name": "通业科技",
          "ret": 0.1267,
          "core": 1.335906
        }
      ]
    },
    {
      "code": "BK1392",
      "name": "工程机械器件",
      "type": "industry",
      "ret": 0.0352,
      "pop": -0.23223,
      "persistence": 3,
      "dispersion": null,
      "breadth": null,
      "score": NaN,
      "stance": "AVOID",
      "is_new": true,
      "core_stocks": []
    },
    {
      "code": "BK1524",
      "name": "汽车综合服务",
      "type": "industry",
      "ret": 0.0347,
      "pop": -0.418015,
      "persistence": 3,
      "dispersion": 0.048315,
      "breadth": 0.8,
      "score": -0.601566,
      "stance": "AVOID",
      "is_new": true,
      "core_stocks": [
        {
          "code": "300825",
          "name": "阿尔特",
          "ret": 0.1316,
          "core": 1.070924
        },
        {
          "code": "600676",
          "name": "交运股份",
          "ret": 0.0162,
          "core": -0.818192
        },
        {
          "code": "301215",
          "name": "中汽股份",
          "ret": 0.02,
          "core": -0.951195
        }
      ]
    },
    {
      "code": "BK1263",
      "name": "摩托车及其他",
      "type": "industry",
      "ret": 0.0323,
      "pop": -0.108374,
      "persistence": 3,
      "dispersion": 0.067626,
      "breadth": 1.0,
      "score": -0.296858,
      "stance": "WATCH",
      "is_new": true,
      "core_stocks": [
        {
          "code": "920058",
          "name": "华洋赛车",
          "ret": 0.2453,
          "core": 3.119256
        },
        {
          "code": "603787",
          "name": "新日股份",
          "ret": 0.0863,
          "core": 1.5496
        },
        {
          "code": "003033",
          "name": "征和工业",
          "ret": 0.1,
          "core": 0.865302
        }
      ]
    }
  ],
  "concept_boards": [
    {
      "code": "BK0429",
      "name": "交运设备",
      "type": "concept",
      "ret": 0.0411,
      "pop": 0.758619,
      "persistence": 3,
      "dispersion": 0.054375,
      "breadth": 1.0,
      "score": 2.054959,
      "stance": "STRONG_BUY",
      "is_new": true,
      "core_stocks": [
        {
          "code": "920027",
          "name": "交大铁发",
          "ret": 0.1715,
          "core": 3.769929
        },
        {
          "code": "920058",
          "name": "华洋赛车",
          "ret": 0.241,
          "core": 3.096728
        },
        {
          "code": "301048",
          "name": "金鹰重工",
          "ret": 0.1998,
          "core": 2.481222
        }
      ]
    },
    {
      "code": "BK0899",
      "name": "CRO",
      "type": "concept",
      "ret": 0.0181,
      "pop": 0.356087,
      "persistence": 3,
      "dispersion": 0.029043,
      "breadth": 1.0,
      "score": 0.389848,
      "stance": "WATCH",
      "is_new": false,
      "core_stocks": [
        {
          "code": "301201",
          "name": "诚达药业",
          "ret": 0.1069,
          "core": 2.039757
        },
        {
          "code": "300683",
          "name": "海特生物",
          "ret": 0.037,
          "core": 1.262815
        },
        {
          "code": "301333",
          "name": "诺思格",
          "ret": 0.0764,
          "core": 0.733667
        }
      ]
    },
    {
      "code": "BK1029",
      "name": "汽车整车",
      "type": "concept",
      "ret": 0.0166,
      "pop": 0.170302,
      "persistence": 3,
      "dispersion": 0.024422,
      "breadth": 1.0,
      "score": 0.124276,
      "stance": "WATCH",
      "is_new": true,
      "core_stocks": [
        {
          "code": "600303",
          "name": "曙光股份",
          "ret": 0.0438,
          "core": 0.679084
        },
        {
          "code": "000957",
          "name": "中通客车",
          "ret": 0.0469,
          "core": 0.265951
        },
        {
          "code": "000572",
          "name": "海马汽车",
          "ret": 0.0197,
          "core": 0.095089
        }
      ]
    },
    {
      "code": "BK0991",
      "name": "工程机械概念",
      "type": "concept",
      "ret": 0.0133,
      "pop": 0.541871,
      "persistence": 3,
      "dispersion": 0.047119,
      "breadth": 1.0,
      "score": 0.091116,
      "stance": "WATCH",
      "is_new": true,
      "core_stocks": [
        {
          "code": "301048",
          "name": "金鹰重工",
          "ret": 0.1998,
          "core": 2.481222
        },
        {
          "code": "920942",
          "name": "恒立钻具",
          "ret": 0.0924,
          "core": 1.793106
        },
        {
          "code": "600528",
          "name": "中铁工业",
          "ret": 0.0995,
          "core": 0.788018
        }
      ]
    },
    {
      "code": "BK0592",
      "name": "铁路基建",
      "type": "concept",
      "ret": 0.0117,
      "pop": 1.718505,
      "persistence": 3,
      "dispersion": null,
      "breadth": null,
      "score": NaN,
      "stance": "AVOID",
      "is_new": true,
      "core_stocks": []
    },
    {
      "code": "BK1637",
      "name": "东方财富热股",
      "type": "concept",
      "ret": 0.0111,
      "pop": 1.161152,
      "persistence": 3,
      "dispersion": 0.029937,
      "breadth": 1.0,
      "score": 1.562996,
      "stance": "STRONG_BUY",
      "is_new": false,
      "core_stocks": [
        {
          "code": "301008",
          "name": "宏昌科技",
          "ret": 0.2001,
          "core": 3.697787
        },
        {
          "code": "603601",
          "name": "再升科技",
          "ret": 0.1,
          "core": 3.604637
        },
        {
          "code": "002263",
          "name": "大东南",
          "ret": 0.1,
          "core": 2.766943
        }
      ]
    },
    {
      "code": "BK0975",
      "name": "磁悬浮概念",
      "type": "concept",
      "ret": 0.0102,
      "pop": -0.108374,
      "persistence": 3,
      "dispersion": 0.034839,
      "breadth": 1.0,
      "score": -1.167624,
      "stance": "AVOID",
      "is_new": true,
      "core_stocks": [
        {
          "code": "300960",
          "name": "通业科技",
          "ret": 0.1251,
          "core": 1.326918
        },
        {
          "code": "002361",
          "name": "神剑股份",
          "ret": 0.1,
          "core": 1.292573
        },
        {
          "code": "600528",
          "name": "中铁工业",
          "ret": 0.0995,
          "core": 0.788018
        }
      ]
    },
    {
      "code": "BK0708",
      "name": "体育产业",
      "type": "concept",
      "ret": 0.0098,
      "pop": 0.758619,
      "persistence": 3,
      "dispersion": 0.053465,
      "breadth": 1.0,
      "score": 0.246699,
      "stance": "WATCH",
      "is_new": true,
      "core_stocks": [
        {
          "code": "920058",
          "name": "华洋赛车",
          "ret": 0.2275,
          "core": 2.986013
        },
        {
          "code": "300651",
          "name": "金陵体育",
          "ret": 0.0681,
          "core": 2.196128
        },
        {
          "code": "600158",
          "name": "中体产业",
          "ret": 0.1,
          "core": 1.445678
        }
      ]
    },
    {
      "code": "BK1147",
      "name": "SPD概念",
      "type": "concept",
      "ret": 0.0098,
      "pop": -0.263194,
      "persistence": 3,
      "dispersion": 0.016538,
      "breadth": 0.9,
      "score": -0.558921,
      "stance": "AVOID",
      "is_new": false,
      "core_stocks": [
        {
          "code": "603122",
          "name": "合富中国",
          "ret": 0.0325,
          "core": 1.060277
        },
        {
          "code": "603716",
          "name": "塞力医疗",
          "ret": 0.0448,
          "core": 0.973849
        },
        {
          "code": "301584",
          "name": "建发致新",
          "ret": 0.04,
          "core": 0.640683
        }
      ]
    },
    {
      "code": "BK1049",
      "name": "EDR概念",
      "type": "concept",
      "ret": 0.0088,
      "pop": -0.356087,
      "persistence": 3,
      "dispersion": null,
      "breadth": null,
      "score": NaN,
      "stance": "AVOID",
      "is_new": true,
      "core_stocks": []
    }
  ],
  "indices": {
    "CSI100": {
      "open": 438000.0,
      "high": 441119.0,
      "low": 434170.0,
      "close": 436382.0,
      "ret": -0.32,
      "volume": 66795191.0,
      "turnover": 198932151671.9
    },
    "HS300": {
      "open": 449192.0,
      "high": 452317.0,
      "low": 446235.0,
      "close": 448369.0,
      "ret": -0.18,
      "volume": 163571310.0,
      "turnover": 357748905797.9
    },
    "CSI500": {
      "open": 774058.0,
      "high": 778889.0,
      "low": 763517.0,
      "close": 768983.0,
      "ret": -0.82,
      "volume": 146803178.0,
      "turnover": 282232350106.7
    },
    "CSI1000": {
      "open": 774196.0,
      "high": 778924.0,
      "low": 763578.0,
      "close": 768748.0,
      "ret": -1.04,
      "volume": 190410195.0,
      "turnover": 304206030522.6
    },
    "CSI2000": {
      "open": 329057.0,
      "high": 331868.0,
      "low": 325032.0,
      "close": 327265.0,
      "ret": -0.74,
      "volume": 252549663.0,
      "turnover": 346930190484.0
    },
    "SHCOMP": {
      "open": 392407.0,
      "high": 394881.0,
      "low": 390437.0,
      "close": 392130.0,
      "ret": -0.05,
      "volume": 449525470.0,
      "turnover": 665141027691.9
    },
    "hs300": {
      "open": 449192.0,
      "high": 452317.0,
      "low": 446235.0,
      "close": 448369.0,
      "ret": -0.18,
      "volume": 163571310.0,
      "turnover": 357748905797.9
    },
    "csi1000": {
      "open": 774196.0,
      "high": 778924.0,
      "low": 763578.0,
      "close": 768748.0,
      "ret": -1.04,
      "volume": 190410195.0,
      "turnover": 304206030522.6
    },
    "shcomp": {
      "open": 392407.0,
      "high": 394881.0,
      "low": 390437.0,
      "close": 392130.0,
      "ret": -0.05,
      "volume": 449525470.0,
      "turnover": 665141027691.9
    }
  },
  "market_indices": {
    "SHCOMP": {
      "name": "上证指数",
      "open": 3924.07,
      "high": 3948.81,
      "low": 3904.37,
      "close": 3921.17,
      "ret": -0.0005,
      "volume": 449607225.0,
      "turnover": 665256801977.9
    },
    "SZCOMP": {
      "name": "深证成指",
      "open": 13683.68,
      "high": 13783.97,
      "low": 13503.57,
      "close": 13599.42,
      "ret": -0.0092,
      "volume": 494728300.0,
      "turnover": 828400925336.0977
    },
    "CYBZ": {
      "name": "创业板指",
      "open": 3247.28,
      "high": 3280.48,
      "low": 3189.2,
      "close": 3215.44,
      "ret": -0.0177,
      "volume": 136151876.0,
      "turnover": 359031020650.3
    },
    "KCB50": {
      "name": "科创50",
      "open": 1283.9,
      "high": 1296.03,
      "low": 1265.77,
      "close": 1272.68,
      "ret": -0.0133,
      "volume": 6686452.0,
      "turnover": 41973900360.0
    },
    "BJ50": {
      "name": "北证50",
      "open": 1261.64,
      "high": 1279.76,
      "low": 1257.05,
      "close": 1261.72,
      "ret": 0.0008,
      "volume": 4467804.0,
      "turnover": 9968745056.0
    }
  },
  "disclaimer": "本页面仅为个人研究与技术演示，不构成投资建议。"
}